zbase/__init__.py
zbase/env.py
zbase/drivers/__init__.py
zbase/drivers/async_mysql.py
zbase/drivers/async_postgre.py
zbase/drivers/async_redis.py
zbase/drivers/db.py
zbase/drivers/email.py
zbase/drivers/json_redis.py
zbase/drivers/mysql.py
zbase/drivers/postgre.py
zbase/drivers/redis.py
zbase/drivers/s3.py
zbase/fastapis/__init__.py
zbase/fastapis/apps.py
zbase/utils/__init__.py
zbase/utils/encrypts.py
zbase/utils/files.py
zbase/utils/hashs.py
zbase/utils/io.py
zbase/utils/jsons.py
zbase/utils/lists.py
zbase/utils/oauth2.py
zbase/utils/rands.py
zbase/utils/shell.py
zbase-0.0.4.dist-info/LICENSE
zbase-0.0.4.dist-info/METADATA
zbase-0.0.4.dist-info/WHEEL
zbase-0.0.4.dist-info/top_level.txt
zbase-0.0.4.dist-info/RECORD
