Metadata-Version: 2.1
Name: zbase
Version: 0.0.4
Summary: foundation library of python project
Home-page: https://github.com/scilive/zbase
Author: Daqian
License: Sci.live license
Keywords: sci.live
Platform: Independant
License-File: LICENSE
Requires-Dist: python-dotenv >=1.0.0
Requires-Dist: sqlalchemy >=2.0.22
Requires-Dist: redis >=5.0.1
Requires-Dist: bcrypt >=4.0.1
Requires-Dist: pytest >=7.4.3
Requires-Dist: fastapi >=0.104.0
Requires-Dist: PyJWT >=2.8.0
Requires-Dist: httpx >=0.25.0
Requires-Dist: PyMySQL >=1.1.0
Requires-Dist: cryptography >=41.0.5
Requires-Dist: minio >=7.2.0
Requires-Dist: yagmail >=0.15.293
